{
    "ch0": [
        [
            57458,
            234
        ],
        [
            759,
            1527
        ]
    ],
    "ch1": [
        [
            57460,
            188
        ],
        [
            583,
            1747
        ]
    ],
    "ch2": [
        [
            57308,
            88
        ],
        [
            901,
            1681
        ]
    ],
    "ch3": [
        [
            57258,
            91
        ],
        [
            891,
            1738
        ]
    ],
    "ch4": [
        [
            57568,
            48
        ],
        [
            691,
            1671
        ]
    ],
    "ch5": [
        [
            57043,
            231
        ],
        [
            776,
            1928
        ]
    ],
    "ch6": [
        [
            56763,
            143
        ],
        [
            1272,
            1800
        ]
    ],
    "ch7": [
        [
            57064,
            204
        ],
        [
            1133,
            1577
        ]
    ],
    "ch8": [
        [
            56986,
            123
        ],
        [
            1278,
            1591
        ]
    ],
    "ch9": [
        [
            56871,
            92
        ],
        [
            1332,
            1683
        ]
    ],
    "ch10": [
        [
            57134,
            211
        ],
        [
            1148,
            1485
        ]
    ],
    "ch11": [
        [
            56974,
            29
        ],
        [
            1260,
            1715
        ]
    ],
    "ch12": [
        [
            56809,
            3
        ],
        [
            873,
            2293
        ]
    ],
    "ch13": [
        [
            57304,
            4
        ],
        [
            512,
            2158
        ]
    ],
    "ch14": [
        [
            57820,
            8
        ],
        [
            566,
            1584
        ]
    ]
}