{
    "ch0": [
        [
            15394,
            279
        ],
        [
            423,
            618
        ]
    ],
    "ch1": [
        [
            15477,
            154
        ],
        [
            467,
            616
        ]
    ],
    "ch2": [
        [
            15338,
            193
        ],
        [
            534,
            649
        ]
    ],
    "ch3": [
        [
            15152,
            372
        ],
        [
            444,
            746
        ]
    ],
    "ch4": [
        [
            15387,
            292
        ],
        [
            368,
            667
        ]
    ],
    "ch5": [
        [
            15237,
            271
        ],
        [
            452,
            754
        ]
    ],
    "ch6": [
        [
            15165,
            18
        ],
        [
            971,
            560
        ]
    ],
    "ch7": [
        [
            15353,
            16
        ],
        [
            830,
            515
        ]
    ],
    "ch8": [
        [
            15225,
            23
        ],
        [
            953,
            513
        ]
    ],
    "ch9": [
        [
            15229,
            30
        ],
        [
            927,
            528
        ]
    ],
    "ch10": [
        [
            15411,
            0
        ],
        [
            1058,
            245
        ]
    ],
    "ch11": [
        [
            15218,
            0
        ],
        [
            1129,
            367
        ]
    ],
    "ch12": [
        [
            15097,
            2
        ],
        [
            884,
            731
        ]
    ],
    "ch13": [
        [
            15366,
            0
        ],
        [
            658,
            690
        ]
    ],
    "ch14": [
        [
            15645,
            1
        ],
        [
            582,
            486
        ]
    ]
}